setup.py
distributions_rp/Binomialdistribution.py
distributions_rp/Gaussiandistribution.py
distributions_rp/Generaldistribution.py
distributions_rp/__init__.py
distributions_rp.egg-info/PKG-INFO
distributions_rp.egg-info/SOURCES.txt
distributions_rp.egg-info/dependency_links.txt
distributions_rp.egg-info/not-zip-safe
distributions_rp.egg-info/top_level.txt