Metadata-Version: 1.0
Name: distributions-rp
Version: 0.1
Summary: Gaussian distributions
Home-page: UNKNOWN
Author: Ritika Pal
Author-email: palritika71@gmail.com
License: UNKNOWN
Platform: UNKNOWN
